autoinject_pymitter/__init__.py
autoinject_pymitter-1.0.0.dist-info/LICENSE
autoinject_pymitter-1.0.0.dist-info/METADATA
autoinject_pymitter-1.0.0.dist-info/WHEEL
autoinject_pymitter-1.0.0.dist-info/entry_points.txt
autoinject_pymitter-1.0.0.dist-info/top_level.txt
autoinject_pymitter-1.0.0.dist-info/RECORD
