Metadata-Version: 2.1
Name: autoinject-pymitter
Version: 1.0.0
Summary: ADI integration for pymitter
Home-page: https://github.com/turnbullerin/autoinject_pymitter
Author: Erin Turnbull
Author-email: erin.a.turnbull@gmail.com
Project-URL: Bug Tracker, https://github.com/turnbullerin/autoinject_pymitter/issues
Classifier: Programming Language :: Python :: 3
Classifier: License :: OSI Approved :: MIT License
Classifier: Operating System :: OS Independent
Requires-Python: >=3.7
License-File: LICENSE
Requires-Dist: autoinject (>=0.2.0)
Requires-Dist: pymitter (>=0.3.0)
